PBaccesslib/__init__.py
PBaccesslib/comm_bridge.py
PBaccesslib/create_input_mx.py
PBaccesslib/doc_operations.py
PBaccesslib/hearbeat_thread.py
PBaccesslib/keithley_bridge.py
PBaccesslib/logg_config.py
PBaccesslib/main.py
PBaccesslib/characteritzation/__init__.py
PBaccesslib/characteritzation/dac_scan.py
PBaccesslib/characteritzation/disc_scan.py
PBaccesslib/characteritzation/ifeed_scan.py
PBaccesslib/characteritzation/main.py
PBaccesslib/characteritzation/logic/__init__.py
PBaccesslib/characteritzation/logic/acquire_data.py
PBaccesslib/characteritzation/logic/test_logic.py
PBaccesslib/characteritzation/logic/use_matrix_operations.py
PBaccesslib/data/chip_reg.npy
PBaccesslib/data/pixel_reg.npy
PBaccesslib/wafer_test/__init__.py
PBaccesslib/wafer_test/connection_check.py
PBaccesslib/wafer_test/main.py
PBaccesslib/wafer_test/program_check.py
PBaccesslib-0.1.4.dist-info/METADATA
PBaccesslib-0.1.4.dist-info/WHEEL
PBaccesslib-0.1.4.dist-info/top_level.txt
PBaccesslib-0.1.4.dist-info/RECORD
