Metadata-Version: 2.1
Name: PBaccesslib
Version: 0.1.4
Summary: This lib controls Probecard.
Home-page: UNKNOWN
License: CC0 1.0 Universal
Platform: UNKNOWN
Classifier: Development Status :: 4 - Beta
Classifier: Programming Language :: Python :: 3
Requires-Python: >=3
Requires-Dist: pandas (==1.4.1)
Requires-Dist: numpy (==1.22.3)
Requires-Dist: python-dateutil (==2.8.2)
Requires-Dist: pytz (==2022.1)
Requires-Dist: six (==1.16.0)
Requires-Dist: typing-extensions (==4.1.1)
Requires-Dist: Excelacceslib (==0.0.4)
Requires-Dist: K2600acceslib (==0.0.3)
Requires-Dist: Commacceslib (==0.0.5)
Requires-Dist: Bconvertacceslib (==0.0.1)
